MANIFEST.in
README.md
README.pypi.rst
requirements.txt
setup.py
hca_bundle_jsonld/__init__.py
hca_bundle_jsonld/bundle_to_rdf.py
hca_bundle_jsonld.egg-info/PKG-INFO
hca_bundle_jsonld.egg-info/SOURCES.txt
hca_bundle_jsonld.egg-info/dependency_links.txt
hca_bundle_jsonld.egg-info/entry_points.txt
hca_bundle_jsonld.egg-info/namespace_packages.txt
hca_bundle_jsonld.egg-info/not-zip-safe
hca_bundle_jsonld.egg-info/requires.txt
hca_bundle_jsonld.egg-info/top_level.txt