Metadata-Version: 1.1
Name: hca-bundle-jsonld
Version: 0.1.2
Summary: Create RDF and JSON-LD from HCA bundles
Home-page: https://github.com/simonjupp/hca-bundle-jsonld
Author: Simon Jupp
Author-email: jupp@ebi.ac.uk
License: Apache License 2.0
Keywords: genomics
Platform: UNKNOWN
Classifier: Intended Audience :: Science/Research
Classifier: License :: OSI Approved :: Apache Software License
Classifier: Natural Language :: English
Classifier: Programming Language :: Python :: 2.7
Classifier: Topic :: Scientific/Engineering :: Bio-Informatics
